LICENSE.txt
setup.cfg
setup.py
test_pyjaw.py
PyJaw.egg-info/PKG-INFO
PyJaw.egg-info/SOURCES.txt
PyJaw.egg-info/dependency_links.txt
PyJaw.egg-info/entry_points.txt
PyJaw.egg-info/not-zip-safe
PyJaw.egg-info/requires.txt
PyJaw.egg-info/top_level.txt
pyjaw/__init__.py
pyjaw/base.py
pyjaw/exc.py
pyjaw/sample_client.py
testdata/v1_session_create.json
testdata/v1_session_destroy.json
testdata/v1_session_set_guestname.json
testdata/v1_session_verify.json
testdata/v1_user_get_inbox.json
testdata/v1_user_get_info.json
testdata/v1_user_get_people.json
testdata/v1_user_get_profile.json
testdata/v1_user_set_profile.json