Metadata-Version: 1.0
Name: PyJaw
Version: 0.1.5
Summary: A Python implementation of the Rejaw API
Home-page: http://code.google.com/p/pyjaw
Author: Lee McFadden
Author-email: spleeman@gmail.com
License: MIT
Platform: UNKNOWN
Classifier: Development Status :: 3 - Alpha
Classifier: Intended Audience :: Developers
Classifier: License :: OSI Approved :: MIT License
Classifier: Natural Language :: English
Classifier: Operating System :: OS Independent
Classifier: Programming Language :: Python
Classifier: Topic :: Internet :: WWW/HTTP :: Dynamic Content
Classifier: Topic :: Software Development :: Libraries :: Python Modules
